{"layout":{"pages":[{"id":"page_nm5mr6b5","sections":[{"id":"section_8d58d5dc","fields":[{"id":"vraHost","display":"valuePickerTree","signpostPosition":"right-middle","state":{"visible":true,"read-only":false}}]},{"id":"section_yn3m13hg","fields":[{"id":"approvalRequest","display":"dropDown","signpostPosition":"right-middle","state":{"visible":true,"read-only":false}}]},{"id":"section_sfgnnhoa","fields":[{"id":"approvalOperation","display":"dropDown","signpostPosition":"right-middle","state":{"visible":true,"read-only":false}}]},{"id":"section_iccbdekc","fields":[{"id":"comment","display":"textField","signpostPosition":"right-middle","state":{"visible":true,"read-only":false}}]}],"title":"General","state":{}}]},"schema":{"vraHost":{"id":"vraHost","type":{"dataType":"reference","referenceType":"VRA:Host"},"label":"vRA Host","constraints":{"required":true},"default":{"type":"scriptAction","id":"com.vmware.vra.extensibility.plugin/getDefaultVraHostFromConfiguration","parameters":[]}},"approvalRequest":{"id":"approvalRequest","type":{"dataType":"string"},"label":"Deployment","constraints":{"required":true},"valueList":{"type":"scriptAction","id":"com.vmware.vra.extensibility.plugin.rest.approval/getApprovalRequestsIdsAndNames","parameters":[{"vraHost":"vraHost","$type":{"dataType":"reference","referenceType":"VRA:Host"}}]}},"approvalOperation":{"id":"approvalOperation","type":{"dataType":"string"},"label":"Operation","constraints":{"required":false},"valueList":["Approve","Reject"]},"comment":{"id":"comment","type":{"dataType":"string"},"label":"Comment","constraints":{"required":false}}},"options":{"externalValidations":[]},"itemId":""}